{
    "topNav":[
        {
            "title":"Explore",
            "link":"/explore",
            "icon": "menu"
        },
        {
            "title":"Memberships",
            "link":"/membership",
            "icon": "user-plus"
        },
        {
            "title":"News",
            "link":"/blog",
            "icon": "list"
        },
        {
            "title":"Contact",
            "link":"/contact",
            "icon": "at-sign",
            "class": "hideSM"
        }
    ],
    "actionNav":[
        {
            "title":"Contact",
            "link":"/contact",
            "icon": "at-sign",
            "class": "ghost hideMD hideLG"
        },
        {
            "title":"Log-in",
            "link":"/portal",
            "icon": "user",
            "class": "ghost"
        },
        {
            "title":"Join",
            "link":"/membership",
            "icon": "user-plus",
            "class": "primary"
        }
    ]
}